mag1c/__init__.py
mag1c/__main__.py
mag1c/ch4.hdr
mag1c/ch4.lut
mag1c/mag1c.py
mag1c/version.py
mag1c-1.2.0.dist-info/LICENSE
mag1c-1.2.0.dist-info/METADATA
mag1c-1.2.0.dist-info/WHEEL
mag1c-1.2.0.dist-info/entry_points.txt
mag1c-1.2.0.dist-info/top_level.txt
mag1c-1.2.0.dist-info/RECORD
