Metadata-Version: 2.1
Name: mag1c
Version: 1.2.0
Summary: A Sparse Matched Filter Algorithm for Atmospheric Trace Gas Concentration Estimation
Home-page: https://github.com/markusfoote/mag1c
Author: Markus Foote
Author-email: markusfoote@gmail.com
License: BSD
Keywords: imaging spectrometer matched filter sparse pytorch
Platform: UNKNOWN
Classifier: Programming Language :: Python :: 3.6
Classifier: Programming Language :: Python :: 3.7
Classifier: License :: OSI Approved :: BSD License
Classifier: Operating System :: OS Independent
Classifier: Environment :: Console
Classifier: Intended Audience :: Science/Research
Classifier: Natural Language :: English
Classifier: Topic :: Scientific/Engineering :: Atmospheric Science
Classifier: Development Status :: 4 - Beta
Requires-Python: >=3.6
Requires-Dist: torch (>=1.3)
Requires-Dist: numpy (>=1.16.4)
Requires-Dist: spectral (>=0.19)
Requires-Dist: scikit-image (>=0.15.0)
